ps_symbolic_modeling_tool/__init__.py
ps_symbolic_modeling_tool/cli.py
ps_symbolic_modeling_tool/converter.py
ps_symbolic_modeling_tool/non_numba_func.py
ps_symbolic_modeling_tool/sym_2_Jac.py
ps_symbolic_modeling_tool/sym_2_func.py
ps_symbolic_modeling_tool-0.2.0.dist-info/COPYING
ps_symbolic_modeling_tool-0.2.0.dist-info/COPYING.LESSER
ps_symbolic_modeling_tool-0.2.0.dist-info/METADATA
ps_symbolic_modeling_tool-0.2.0.dist-info/WHEEL
ps_symbolic_modeling_tool-0.2.0.dist-info/entry_points.txt
ps_symbolic_modeling_tool-0.2.0.dist-info/top_level.txt
ps_symbolic_modeling_tool-0.2.0.dist-info/RECORD
