Metadata-Version: 2.1
Name: ps_symbolic_modeling_tool
Version: 0.2.0
Summary: This package converts symbolic functions written in sympy to their numerical versions and also generates the Jacobian matrix.
Home-page: https://github.com/th1275/ps_symbolic_modeling_tool
Author: Tianqi Hong, Jing Xiong
Author-email: tianqi.hong@uga.edu, jxiong20@outlook.com
License: LGPL-3.0-or-later
Classifier: Programming Language :: Python :: 3
Classifier: License :: OSI Approved :: GNU Lesser General Public License v3 (LGPLv3)
Classifier: Operating System :: OS Independent
Requires-Python: >=3.6
License-File: COPYING
License-File: COPYING.LESSER
Requires-Dist: sympy
